tivars/__init__.py
tivars/data.py
tivars/flags.py
tivars/flash.py
tivars/numeric.py
tivars/var.py
tivars/PIL/TI8caPlugin.py
tivars/PIL/TI8ciPlugin.py
tivars/PIL/TI8xiPlugin.py
tivars/PIL/__init__.py
tivars/PIL/common.py
tivars/models/__init__.py
tivars/models/model.py
tivars/models/versions.py
tivars/tokenizer/__init__.py
tivars/tokenizer/decoder.py
tivars/tokenizer/encoder.py
tivars/tokenizer/state.py
tivars/tokens/8X.xml
tivars/tokens/scripts/__init__.py
tivars/tokens/scripts/build.py
tivars/tokens/scripts/formats.py
tivars/tokens/scripts/parse.py
tivars/tokens/scripts/tokenide.py
tivars/tokens/scripts/trie.py
tivars/types/__init__.py
tivars/types/appvar.py
tivars/types/complex.py
tivars/types/flash.py
tivars/types/gdb.py
tivars/types/group.py
tivars/types/list.py
tivars/types/matrix.py
tivars/types/picture.py
tivars/types/real.py
tivars/types/settings.py
tivars/types/tokenized.py
tivars/types/json/func.default.json
tivars/types/json/param.default.json
tivars/types/json/polar.default.json
tivars/types/json/seq.default.json
tivars-0.9.2.dist-info/LICENSE
tivars-0.9.2.dist-info/METADATA
tivars-0.9.2.dist-info/WHEEL
tivars-0.9.2.dist-info/top_level.txt
tivars-0.9.2.dist-info/RECORD
