Metadata-Version: 2.1
Name: tivars
Version: 0.9.2
Summary: A library for interacting with TI-(e)z80 (82/83/84 series) calculator files
License: The MIT License (MIT)
Project-URL: Repository, https://github.com/TI-Toolkit/tivars_lib_py
Project-URL: Documentation, https://ti-toolkit.github.io/tivars_lib_py/
Requires-Python: >=3.10
License-File: LICENSE
Provides-Extra: images
Requires-Dist: pillow; extra == "images"
Requires-Dist: numpy; extra == "images"
Provides-Extra: arrays
Requires-Dist: numpy; extra == "arrays"
